bridge/__init__.py
bridge/dist/bridge.bundle.cjs
swarmkit/__init__.py
swarmkit/agent.py
swarmkit/bridge.py
swarmkit/composio.py
swarmkit/config.py
swarmkit/results.py
swarmkit/retry.py
swarmkit/schema.py
swarmkit/utils.py
swarmkit/pipeline/__init__.py
swarmkit/pipeline/pipeline.py
swarmkit/pipeline/types.py
swarmkit/prompts/__init__.py
swarmkit/prompts/agent_md/judge.md
swarmkit/prompts/agent_md/reduce.md
swarmkit/prompts/agent_md/verify.md
swarmkit/prompts/user/judge.md
swarmkit/prompts/user/retry_feedback.md
swarmkit/prompts/user/verify.md
swarmkit/swarm/__init__.py
swarmkit/swarm/results.py
swarmkit/swarm/swarm.py
swarmkit/swarm/types.py
swarmkit-0.1.62.dist-info/licenses/LICENSE
swarmkit-0.1.62.dist-info/METADATA
swarmkit-0.1.62.dist-info/WHEEL
swarmkit-0.1.62.dist-info/top_level.txt
swarmkit-0.1.62.dist-info/RECORD
