Metadata-Version: 2.4
Name: swarmkit
Version: 0.1.62
Summary: Pythonic wrapper around the TypeScript SwarmKit SDK for multi-agent orchestration in E2B sandboxes
Author-email: "Evolving Machines, Inc." <brandomagnani@evolvingmachines.ai>
License: Proprietary Beta Evaluation License - See LICENSE file
Project-URL: Homepage, https://github.com/brandomagnani/swarmkit.git
Project-URL: Repository, https://github.com/brandomagnani/swarmkit.git
Keywords: ai,agents,sandbox,e2b,orchestration,codex,claude,gemini
Classifier: Development Status :: 4 - Beta
Classifier: Intended Audience :: Developers
Classifier: License :: Other/Proprietary License
Classifier: Programming Language :: Python :: 3
Classifier: Programming Language :: Python :: 3.11
Classifier: Programming Language :: Python :: 3.12
Classifier: Topic :: Software Development :: Libraries :: Python Modules
Requires-Python: >=3.11
License-File: LICENSE
Provides-Extra: dev
Requires-Dist: pytest>=8.0.0; extra == "dev"
Requires-Dist: pytest-asyncio>=0.23.0; extra == "dev"
Requires-Dist: python-dotenv>=1.0.0; extra == "dev"
Requires-Dist: pydantic>=2.0.0; extra == "dev"
Dynamic: license-file
